{
  "lastUpdated": "2025-10-02T13:12:16.669Z",
  "sheetName": "Tabell HT25 ",
  "sections": {
    "mainStats": {
      "title": "Statistik",
      "totalRows": 9,
      "data": [
        {
          "#": 1,
          "Spelare": "Aleks / Amanda",
          "Poäng": 0,
          "SM": 2,
          "Vinster": 0,
          "Oavgjort": 0,
          "Förlust": 2,
          "Sets": -4,
          "GA": 18,
          "GC": 44,
          "G/D": -26
        },
        {
          "#": 2,
          "Spelare": "Mood / Robert",
          "Poäng": 0,
          "SM": 1,
          "Vinster": 0,
          "Oavgjort": 0,
          "Förlust": 1,
          "Sets": -2,
          "GA": 12,
          "GC": 22,
          "G/D": -10
        },
        {
          "#": 4,
          "Spelare": "Kristian / Silvan",
          "Poäng": 3,
          "SM": 2,
          "Vinster": 1,
          "Oavgjort": 0,
          "Förlust": 1,
          "Sets": 1,
          "GA": 49,
          "GC": 42,
          "G/D": 7
        },
        {
          "#": 3,
          "Spelare": "Daniel / Hyberg",
          "Poäng": 3,
          "SM": 1,
          "Vinster": 1,
          "Oavgjort": 0,
          "Förlust": 0,
          "Sets": 2,
          "GA": 22,
          "GC": 9,
          "G/D": 13
        },
        {
          "#": 5,
          "Spelare": "Martin F / Fredrik",
          "Poäng": 3,
          "SM": 1,
          "Vinster": 1,
          "Oavgjort": 0,
          "Förlust": 0,
          "Sets": 2,
          "GA": 22,
          "GC": 12,
          "G/D": 10
        },
        {
          "#": 6,
          "Spelare": "Mark / Haubir",
          "Poäng": 6,
          "SM": 2,
          "Vinster": 2,
          "Oavgjort": 0,
          "Förlust": 0,
          "Sets": 1,
          "GA": 55,
          "GC": 41,
          "G/D": 14
        },
        {
          "#": 7,
          "Spelare": "Lucas / Dara",
          "Poäng": 0,
          "SM": 1,
          "Vinster": 0,
          "Oavgjort": 0,
          "Förlust": 1,
          "Sets": -2,
          "GA": 12,
          "GC": 22,
          "G/D": -10
        },
        {
          "#": 8,
          "Spelare": "Anton / Jonas",
          "Poäng": 0,
          "SM": 1,
          "Vinster": 0,
          "Oavgjort": 0,
          "Förlust": 1,
          "Sets": 0,
          "GA": 14,
          "GC": 22,
          "G/D": -8
        },
        {
          "#": 9,
          "Spelare": "Anders K / George",
          "Poäng": 3,
          "SM": 1,
          "Vinster": 1,
          "Oavgjort": 0,
          "Förlust": 0,
          "Sets": 2,
          "GA": 22,
          "GC": 12,
          "G/D": 10
        }
      ]
    },
    "largeTable": {
      "title": "Resultat",
      "totalRows": 36,
      "data": [
        {
          "Lag": 1,
          "Vinnare": "Anders K / George",
          "Förlorare": "Mood / Robert",
          "Resultat": "2-0",
          "TotPoäng": "22-12"
        },
        {
          "Lag": 2,
          "Vinnare": "Mark / Haubir",
          "Förlorare": "Anton / Jonas",
          "Resultat": "2-0",
          "TotPoäng": "22-14"
        },
        {
          "Lag": 3,
          "Vinnare": "Martin F / Fredrik",
          "Förlorare": "Lucas / Dara",
          "Resultat": "2-0",
          "TotPoäng": "22-12"
        },
        {
          "Lag": 4,
          "Vinnare": "Mark / Haubir",
          "Förlorare": "Kristian / Silvan",
          "Resultat": "2-1",
          "TotPoäng": "33-27"
        },
        {
          "Lag": 5,
          "Vinnare": "Kristian / Silvan",
          "Förlorare": "Aleks / Amanda",
          "Resultat": "2-0",
          "TotPoäng": "22-9"
        },
        {
          "Lag": 6,
          "Vinnare": "Daniel / Hyberg",
          "Förlorare": "Aleks / Amanda",
          "Resultat": "2-0",
          "TotPoäng": "22-9"
        },
        {
          "Lag": 7
        },
        {
          "Lag": 8
        },
        {
          "Lag": 9
        },
        {
          "Lag": 10
        },
        {
          "Lag": 11
        },
        {
          "Lag": 12
        },
        {
          "Lag": 13
        },
        {
          "Lag": 14
        },
        {
          "Lag": 15
        },
        {
          "Lag": 16
        },
        {
          "Lag": 17
        },
        {
          "Lag": 18
        },
        {
          "Lag": 19
        },
        {
          "Lag": 20
        },
        {
          "Lag": 21
        },
        {
          "Lag": 22
        },
        {
          "Lag": 23
        },
        {
          "Lag": 24
        },
        {
          "Lag": 25
        },
        {
          "Lag": 26
        },
        {
          "Lag": 27
        },
        {
          "Lag": 28
        },
        {
          "Lag": 29
        },
        {
          "Lag": 30
        },
        {
          "Lag": 31
        },
        {
          "Lag": 32
        },
        {
          "Lag": 33
        },
        {
          "Lag": 34
        },
        {
          "Lag": 35
        },
        {
          "Lag": 36
        }
      ]
    },
    "smallTable": {
      "title": "Ranking",
      "totalRows": 9,
      "data": [
        {
          "Ranking": "🥇",
          "Spelare": "Mark / Haubir"
        },
        {
          "Ranking": "🥈",
          "Spelare": "Daniel / Hyberg"
        },
        {
          "Ranking": "🥉",
          "Spelare": "Martin F / Fredrik"
        },
        {
          "Ranking": 4,
          "Spelare": "Anders K / George"
        },
        {
          "Ranking": 5,
          "Spelare": "Kristian / Silvan"
        },
        {
          "Ranking": 6,
          "Spelare": "Anton / Jonas"
        },
        {
          "Ranking": 7,
          "Spelare": "Mood / Robert"
        },
        {
          "Ranking": 8,
          "Spelare": "Lucas / Dara"
        },
        {
          "Ranking": 9,
          "Spelare": "Aleks / Amanda"
        }
      ]
    }
  }
}