{
  "lastUpdated": "2025-11-24T07:24:47.830Z",
  "sheetName": "Tabell HT25 ",
  "sections": {
    "mainStats": {
      "title": "Statistik",
      "totalRows": 9,
      "data": [
        {
          "#": 3,
          "Spelare": "Daniel / Hyberg",
          "Poäng": 12,
          "SM": 5,
          "Vinster": 4,
          "Oavgjort": 0,
          "Förlust": 1,
          "Sets": 2,
          "GA": 97,
          "GC": 80,
          "G/D": 17
        },
        {
          "#": 4,
          "Spelare": "Kristian / Silvan",
          "Poäng": 12,
          "SM": 4,
          "Vinster": 4,
          "Oavgjort": 0,
          "Förlust": 0,
          "Sets": 4,
          "GA": 70,
          "GC": 46,
          "G/D": 24
        },
        {
          "#": 6,
          "Spelare": "Mark / Emil",
          "Poäng": 0,
          "SM": 0,
          "Vinster": 0,
          "Oavgjort": 0,
          "Förlust": 0,
          "Sets": 0,
          "GA": 0,
          "GC": 0,
          "G/D": 0
        },
        {
          "#": 2,
          "Spelare": "Mood / Robert",
          "Poäng": 3,
          "SM": 3,
          "Vinster": 1,
          "Oavgjort": 0,
          "Förlust": 2,
          "Sets": -1,
          "GA": 58,
          "GC": 68,
          "G/D": -10
        },
        {
          "#": 5,
          "Spelare": "Martin F / Fredrik",
          "Poäng": 3,
          "SM": 1,
          "Vinster": 1,
          "Oavgjort": 0,
          "Förlust": 0,
          "Sets": 0,
          "GA": 0,
          "GC": 0,
          "G/D": 0
        },
        {
          "#": 8,
          "Spelare": "Anton / Jonas",
          "Poäng": 3,
          "SM": 4,
          "Vinster": 1,
          "Oavgjort": 0,
          "Förlust": 3,
          "Sets": 0,
          "GA": 72,
          "GC": 65,
          "G/D": 7
        },
        {
          "#": 9,
          "Spelare": "Anders K / George",
          "Poäng": 9,
          "SM": 5,
          "Vinster": 3,
          "Oavgjort": 0,
          "Förlust": 2,
          "Sets": 0,
          "GA": 78,
          "GC": 85,
          "G/D": -7
        },
        {
          "#": 1,
          "Spelare": "Aleks / Amanda",
          "Poäng": 0,
          "SM": 5,
          "Vinster": 0,
          "Oavgjort": 0,
          "Förlust": 5,
          "Sets": -5,
          "GA": 35,
          "GC": 66,
          "G/D": -31
        },
        {
          "#": 7,
          "Spelare": "Lucas / Dara",
          "Poäng": 0,
          "SM": 1,
          "Vinster": 0,
          "Oavgjort": 0,
          "Förlust": 1,
          "Sets": 0,
          "GA": 0,
          "GC": 0,
          "G/D": 0
        }
      ]
    },
    "largeTable": {
      "title": "Resultat",
      "totalRows": 36,
      "data": [
        {
          "Lag": 1,
          "Vinnare": "Anders K / George",
          "Förlorare": "Mood / Robert",
          "Resultat": "2-0",
          "TotPoäng": "22-12"
        },
        {
          "Lag": 2,
          "Vinnare": "Martin F / Fredrik",
          "Förlorare": "Lucas / Dara",
          "Resultat": "2-1",
          "TotPoäng": "22-12"
        },
        {
          "Lag": 3,
          "Vinnare": "Kristian / Silvan",
          "Förlorare": "Aleks / Amanda",
          "Resultat": "2-0",
          "TotPoäng": "22-9"
        },
        {
          "Lag": 4,
          "Vinnare": "Daniel / Hyberg",
          "Förlorare": "Aleks / Amanda",
          "Resultat": "2-0",
          "TotPoäng": "22-9"
        },
        {
          "Lag": 5,
          "Vinnare": "Anton / Jonas",
          "Förlorare": "Aleks / Amanda",
          "Resultat": "2-0",
          "TotPoäng": "22-14"
        },
        {
          "Lag": 6,
          "Vinnare": "Daniel / Hyberg",
          "Förlorare": "Anders K / George",
          "Resultat": "2-1",
          "TotPoäng": "32-24"
        },
        {
          "Lag": 7,
          "Vinnare": "Mood / Robert",
          "Förlorare": "Aleks / Amanda",
          "Resultat": "2-1",
          "TotPoäng": "29-25"
        },
        {
          "Lag": 8,
          "Vinnare": "Daniel / Hyberg",
          "Förlorare": "Mood / Robert",
          "Resultat": "2-1",
          "TotPoäng": "26-20"
        },
        {
          "Lag": 9,
          "Vinnare": "Daniel / Hyberg",
          "Förlorare": "Anton / Jonas",
          "Resultat": "2-1",
          "TotPoäng": "27-25"
        },
        {
          "Lag": 10,
          "Vinnare": "Kristian / Silvan",
          "Förlorare": "Anders K / George",
          "Resultat": "2-0",
          "TotPoäng": "22-14"
        },
        {
          "Lag": 11,
          "Vinnare": "Anders K / George",
          "Förlorare": "Anton / Jonas",
          "Resultat": "2-0",
          "TotPoäng": "23-17"
        },
        {
          "Lag": 12,
          "Vinnare": "Kristian / Silvan",
          "Förlorare": "Daniel / Hyberg",
          "Resultat": "2-1",
          "TotPoäng": "33-32"
        },
        {
          "Lag": 13,
          "Vinnare": "Kristian / Silvan",
          "Förlorare": "Anton / Jonas",
          "Resultat": "2-1",
          "TotPoäng": "34-29"
        },
        {
          "Lag": 14,
          "Vinnare": "Anders K / George",
          "Förlorare": "Aleks / Amanda",
          "Resultat": "2-0",
          "TotPoäng": "25-16"
        },
        {
          "Lag": 15
        },
        {
          "Lag": 16
        },
        {
          "Lag": 17
        },
        {
          "Lag": 18
        },
        {
          "Lag": 19
        },
        {
          "Lag": 20
        },
        {
          "Lag": 21
        },
        {
          "Lag": 22
        },
        {
          "Lag": 23
        },
        {
          "Lag": 24
        },
        {
          "Lag": 25
        },
        {
          "Lag": 26
        },
        {
          "Lag": 27
        },
        {
          "Lag": 28
        },
        {
          "Lag": 29
        },
        {
          "Lag": 30
        },
        {
          "Lag": 31
        },
        {
          "Lag": 32
        },
        {
          "Lag": 33
        },
        {
          "Lag": 34
        },
        {
          "Lag": 35
        },
        {
          "Lag": 36
        }
      ]
    },
    "smallTable": {
      "title": "Ranking",
      "totalRows": 9,
      "data": [
        {
          "Ranking": 1,
          "Spelare": "Kristian / Silvan"
        },
        {
          "Ranking": 2,
          "Spelare": "Daniel / Hyberg"
        },
        {
          "Ranking": 3,
          "Spelare": "Anders K / George"
        },
        {
          "Ranking": 4,
          "Spelare": "Anton / Jonas"
        },
        {
          "Ranking": 5,
          "Spelare": "Martin F / Fredrik"
        },
        {
          "Ranking": 6,
          "Spelare": "Mood / Robert"
        },
        {
          "Ranking": 7,
          "Spelare": "Mark / Emil"
        },
        {
          "Ranking": 8,
          "Spelare": "Lucas / Dara"
        },
        {
          "Ranking": 9,
          "Spelare": "Aleks / Amanda"
        }
      ]
    }
  }
}